setup.py
mpd_muspy/__init__.py
mpd_muspy/__main__.py
mpd_muspy/artist_db.py
mpd_muspy/exceptions.py
mpd_muspy/muspy_api.py
mpd_muspy/presync.py
mpd_muspy/sync.py
mpd_muspy/tools.py
mpd_muspy.egg-info/PKG-INFO
mpd_muspy.egg-info/SOURCES.txt
mpd_muspy.egg-info/dependency_links.txt
mpd_muspy.egg-info/entry_points.txt
mpd_muspy.egg-info/requires.txt
mpd_muspy.egg-info/top_level.txt