Metadata-Version: 1.1
Name: mpd-muspy
Version: 1.0.2
Summary: Sync artists of your MPD database with your MuSpy account
Home-page: https://github.com/Anthony25/mpd-muspy
Author: Anthony25 <Anthony Ruhier>
Author-email: anthony.ruhier@gmail.com
License: Simplified BSD
Keywords: mpd
Platform: UNKNOWN
Classifier: Operating System :: POSIX :: Linux
Classifier: Programming Language :: Python :: 3 :: Only
Classifier: License :: OSI Approved :: BSD License
